{
	"type": "FeatureCollection",
	"features": [
		{
			"type": "Feature",
			"properties": {
				"name": "2010-04-26"
			},
			"geometry": {
				"type": "LineString",
				"coordinates": [
					[
						4.145188,
						43.51263
					],
					[
						4.145188,
						43.51263
					],
					[
						4.145186,
						43.51263
					],
					[
						4.145186,
						43.51263
					],
					[
						4.145185,
						43.512631
					],
					[
						4.145183,
						43.512631
					],
					[
						4.145183,
						43.512631
					],
					[
						4.145183,
						43.512631
					],
					[
						4.14509,
						43.512083
					],
					[
						4.145091,
						43.512083
					],
					[
						4.145093,
						43.512083
					],
					[
						4.145096,
						43.512083
					],
					[
						4.145098,
						43.512083
					],
					[
						4.145101,
						43.512083
					],
					[
						4.145104,
						43.512083
					],
					[
						4.145108,
						43.512083
					],
					[
						4.150233,
						43.529906
					],
					[
						4.150233,
						43.529906
					],
					[
						4.150233,
						43.529906
					],
					[
						4.150233,
						43.529906
					],
					[
						4.150235,
						43.529906
					],
					[
						4.150235,
						43.529906
					],
					[
						4.150235,
						43.529906
					],
					[
						4.150235,
						43.529906
					],
					[
						4.139848,
						43.544738
					],
					[
						4.139828,
						43.544818
					],
					[
						4.139813,
						43.544858
					],
					[
						4.139828,
						43.544909
					],
					[
						4.139824,
						43.544971
					],
					[
						4.139808,
						43.545028
					],
					[
						4.139796,
						43.545085
					],
					[
						4.139753,
						43.545143
					],
					[
						4.116913,
						43.551515
					],
					[
						4.116829,
						43.551545
					],
					[
						4.116768,
						43.551568
					],
					[
						4.116721,
						43.551576
					],
					[
						4.11668,
						43.551593
					],
					[
						4.116625,
						43.551611
					],
					[
						4.116593,
						43.551636
					],
					[
						4.116526,
						43.551646
					],
					[
						4.090414,
						43.5636
					],
					[
						4.090358,
						43.56358
					],
					[
						4.090273,
						43.563598
					],
					[
						4.09022,
						43.563601
					],
					[
						4.090128,
						43.56362
					],
					[
						4.090088,
						43.5636
					],
					[
						4.090035,
						43.563604
					],
					[
						4.089959,
						43.563616
					],
					[
						4.075768,
						43.561358
					],
					[
						4.0756,
						43.561396
					],
					[
						4.075548,
						43.561405
					],
					[
						4.07546,
						43.561408
					],
					[
						4.075358,
						43.561411
					],
					[
						4.075293,
						43.561409
					],
					[
						4.075221,
						43.561413
					],
					[
						4.07514,
						43.561416
					],
					[
						4.049823,
						43.557906
					],
					[
						4.049823,
						43.557906
					],
					[
						4.049823,
						43.557906
					],
					[
						4.049823,
						43.557906
					],
					[
						4.049824,
						43.557904
					],
					[
						4.049824,
						43.557904
					],
					[
						4.049824,
						43.557904
					],
					[
						4.049824,
						43.557906
					],
					[
						4.049913,
						43.557828
					],
					[
						4.049911,
						43.557828
					],
					[
						4.049911,
						43.55783
					],
					[
						4.049911,
						43.557831
					],
					[
						4.049909,
						43.557831
					],
					[
						4.049909,
						43.557833
					],
					[
						4.049908,
						43.557835
					],
					[
						4.049908,
						43.557835
					],
					[
						4.035331,
						43.556923
					],
					[
						4.035193,
						43.556944
					],
					[
						4.035138,
						43.556951
					],
					[
						4.035113,
						43.556955
					],
					[
						4.035063,
						43.556953
					],
					[
						4.035015,
						43.556941
					],
					[
						4.034961,
						43.556944
					],
					[
						4.034909,
						43.556948
					],
					[
						4.0301,
						43.556928
					],
					[
						4.030101,
						43.556928
					],
					[
						4.030101,
						43.556928
					],
					[
						4.030101,
						43.556928
					],
					[
						4.030101,
						43.556928
					],
					[
						4.030101,
						43.556928
					],
					[
						4.030103,
						43.556928
					],
					[
						4.030103,
						43.556926
					],
					[
						4.030101,
						43.556825
					],
					[
						4.030101,
						43.556825
					],
					[
						4.030101,
						43.556825
					],
					[
						4.030101,
						43.556825
					],
					[
						4.030101,
						43.556825
					],
					[
						4.030103,
						43.556825
					],
					[
						4.030104,
						43.556825
					],
					[
						4.030106,
						43.556825
					],
					[
						4.029593,
						43.557063
					],
					[
						4.029593,
						43.557063
					],
					[
						4.029593,
						43.557063
					],
					[
						4.029593,
						43.557063
					],
					[
						4.029594,
						43.557063
					],
					[
						4.029599,
						43.557061
					],
					[
						4.029603,
						43.557059
					],
					[
						4.029608,
						43.557059
					],
					[
						4.027146,
						43.558896
					],
					[
						4.027173,
						43.558878
					],
					[
						4.027201,
						43.55886
					],
					[
						4.027229,
						43.558841
					],
					[
						4.027256,
						43.558823
					],
					[
						4.027285,
						43.558805
					],
					[
						4.027311,
						43.558786
					],
					[
						4.027339,
						43.558768
					],
					[
						4.004011,
						43.552114
					],
					[
						4.003973,
						43.552068
					],
					[
						4.003893,
						43.552063
					],
					[
						4.003851,
						43.552054
					],
					[
						4.004316,
						43.55193
					],
					[
						4.004271,
						43.551918
					],
					[
						4.004115,
						43.551918
					],
					[
						4.004079,
						43.551908
					],
					[
						3.980121,
						43.543585
					],
					[
						3.980033,
						43.543684
					],
					[
						3.979333,
						43.544061
					],
					[
						3.978721,
						43.544391
					],
					[
						3.978283,
						43.544718
					],
					[
						3.975674,
						43.545818
					],
					[
						3.977246,
						43.545453
					],
					[
						3.977351,
						43.54536
					],
					[
						3.968526,
						43.553366
					],
					[
						3.967529,
						43.553829
					],
					[
						3.967198,
						43.554053
					],
					[
						3.966671,
						43.554213
					],
					[
						3.966361,
						43.554371
					],
					[
						3.967671,
						43.553808
					],
					[
						3.967409,
						43.5539
					],
					[
						3.967339,
						43.553893
					],
					[
						3.944773,
						43.5682
					],
					[
						3.944434,
						43.568366
					],
					[
						3.944314,
						43.568474
					],
					[
						3.944184,
						43.568566
					],
					[
						3.944029,
						43.568663
					],
					[
						3.943831,
						43.568758
					],
					[
						3.946176,
						43.567828
					],
					[
						3.946203,
						43.567811
					],
					[
						3.937694,
						43.577616
					],
					[
						3.937418,
						43.578121
					],
					[
						3.937454,
						43.578163
					],
					[
						3.937513,
						43.578198
					],
					[
						3.937559,
						43.578238
					],
					[
						3.937611,
						43.578274
					],
					[
						3.937668,
						43.578308
					],
					[
						3.937733,
						43.578334
					],
					[
						3.942391,
						43.586061
					],
					[
						3.941079,
						43.58675
					],
					[
						3.940588,
						43.58699
					],
					[
						3.941304,
						43.586693
					],
					[
						3.941293,
						43.586728
					],
					[
						3.941306,
						43.586758
					],
					[
						3.941306,
						43.586758
					],
					[
						3.941288,
						43.58694
					],
					[
						3.96469,
						43.603193
					],
					[
						3.963856,
						43.603646
					],
					[
						3.963571,
						43.603813
					],
					[
						3.964293,
						43.603513
					],
					[
						3.964348,
						43.603543
					],
					[
						3.96439,
						43.603563
					],
					[
						3.96439,
						43.603563
					],
					[
						3.96439,
						43.603563
					],
					[
						3.942928,
						43.616104
					],
					[
						3.942841,
						43.616048
					],
					[
						3.942793,
						43.616033
					],
					[
						3.942749,
						43.616008
					],
					[
						3.942704,
						43.61599
					],
					[
						3.942668,
						43.615961
					],
					[
						3.942631,
						43.615916
					],
					[
						3.942594,
						43.615883
					],
					[
						3.919478,
						43.60622
					],
					[
						3.918485,
						43.605845
					],
					[
						3.918424,
						43.605646
					],
					[
						3.917993,
						43.605631
					],
					[
						3.917778,
						43.605599
					],
					[
						3.917553,
						43.605385
					],
					[
						3.916545,
						43.60496
					],
					[
						3.916885,
						43.605091
					],
					[
						3.906456,
						43.606516
					],
					[
						3.906373,
						43.60651
					],
					[
						3.906343,
						43.606336
					],
					[
						3.906285,
						43.606389
					],
					[
						3.906273,
						43.606388
					],
					[
						3.906169,
						43.6065
					],
					[
						3.906084,
						43.606586
					],
					[
						3.906126,
						43.606596
					],
					[
						3.894448,
						43.604989
					],
					[
						3.894448,
						43.604989
					],
					[
						3.894448,
						43.604989
					],
					[
						3.894448,
						43.604989
					],
					[
						3.894448,
						43.604989
					],
					[
						3.894446,
						43.605011
					],
					[
						3.894444,
						43.605031
					],
					[
						3.894443,
						43.605051
					],
					[
						3.884833,
						43.610398
					],
					[
						3.884888,
						43.610416
					],
					[
						3.884884,
						43.61042
					],
					[
						3.884851,
						43.610428
					],
					[
						3.884876,
						43.610433
					],
					[
						3.884894,
						43.610426
					],
					[
						3.884923,
						43.610428
					],
					[
						3.884925,
						43.610428
					],
					[
						3.883853,
						43.603176
					],
					[
						3.883853,
						43.603176
					],
					[
						3.883853,
						43.603176
					],
					[
						3.883853,
						43.603176
					],
					[
						3.883855,
						43.603176
					],
					[
						3.883855,
						43.603176
					],
					[
						3.883855,
						43.603178
					],
					[
						3.883855,
						43.603178
					],
					[
						3.879218,
						43.603823
					],
					[
						3.879219,
						43.603823
					],
					[
						3.879221,
						43.603821
					],
					[
						3.879223,
						43.603821
					],
					[
						3.879225,
						43.603819
					],
					[
						3.879226,
						43.603819
					],
					[
						3.879229,
						43.603818
					],
					[
						3.879231,
						43.603818
					],
					[
						3.878153,
						43.606815
					],
					[
						3.878153,
						43.606815
					],
					[
						3.878153,
						43.606815
					],
					[
						3.878153,
						43.606813
					],
					[
						3.878155,
						43.606813
					],
					[
						3.878155,
						43.606813
					],
					[
						3.878155,
						43.606813
					],
					[
						3.878156,
						43.606811
					],
					[
						3.879246,
						43.607868
					],
					[
						3.879246,
						43.607868
					],
					[
						3.879245,
						43.607866
					],
					[
						3.879245,
						43.607866
					],
					[
						3.879245,
						43.607865
					],
					[
						3.879243,
						43.607863
					],
					[
						3.879243,
						43.607863
					],
					[
						3.879241,
						43.607865
					],
					[
						3.881774,
						43.614248
					],
					[
						3.881774,
						43.614248
					],
					[
						3.881776,
						43.614248
					],
					[
						3.881778,
						43.614248
					],
					[
						3.881778,
						43.614248
					],
					[
						3.881779,
						43.614248
					],
					[
						3.881781,
						43.614248
					],
					[
						3.881781,
						43.614248
					],
					[
						3.878853,
						43.614263
					],
					[
						3.878854,
						43.614263
					],
					[
						3.878854,
						43.614264
					],
					[
						3.878854,
						43.614264
					],
					[
						3.878854,
						43.614266
					],
					[
						3.878854,
						43.614266
					],
					[
						3.878854,
						43.614268
					],
					[
						3.878854,
						43.614268
					],
					[
						3.878886,
						43.614205
					],
					[
						3.878886,
						43.614205
					],
					[
						3.878886,
						43.614203
					],
					[
						3.878886,
						43.614203
					],
					[
						3.878885,
						43.614201
					],
					[
						3.878885,
						43.614199
					],
					[
						3.878885,
						43.614198
					],
					[
						3.878885,
						43.614191
					],
					[
						3.877924,
						43.613096
					],
					[
						3.877933,
						43.613105
					],
					[
						3.877945,
						43.613114
					],
					[
						3.877958,
						43.613126
					],
					[
						3.877971,
						43.61314
					],
					[
						3.877986,
						43.613153
					],
					[
						3.878001,
						43.613166
					],
					[
						3.878018,
						43.61318
					],
					[
						3.877251,
						43.613485
					],
					[
						3.878445,
						43.613776
					],
					[
						3.878554,
						43.613838
					],
					[
						3.878685,
						43.613914
					],
					[
						3.878685,
						43.613914
					],
					[
						3.878686,
						43.613916
					],
					[
						3.878688,
						43.613916
					],
					[
						3.878691,
						43.613918
					],
					[
						3.879316,
						43.614308
					],
					[
						3.879351,
						43.614391
					],
					[
						3.879399,
						43.614463
					],
					[
						3.879416,
						43.614479
					],
					[
						3.879428,
						43.614464
					],
					[
						3.879435,
						43.614479
					],
					[
						3.879451,
						43.614513
					],
					[
						3.87947,
						43.614548
					],
					[
						3.879273,
						43.614553
					],
					[
						3.879273,
						43.614553
					],
					[
						3.879273,
						43.614553
					],
					[
						3.879273,
						43.614553
					],
					[
						3.879273,
						43.614553
					],
					[
						3.879273,
						43.614554
					],
					[
						3.879274,
						43.614554
					],
					[
						3.879274,
						43.614554
					],
					[
						3.880713,
						43.614581
					],
					[
						3.880708,
						43.614583
					],
					[
						3.880705,
						43.614583
					],
					[
						3.880699,
						43.614585
					],
					[
						3.880694,
						43.614585
					],
					[
						3.880691,
						43.614586
					],
					[
						3.880686,
						43.614588
					],
					[
						3.880683,
						43.614588
					],
					[
						3.877943,
						43.614888
					],
					[
						3.877943,
						43.614888
					],
					[
						3.877945,
						43.614888
					],
					[
						3.877945,
						43.614888
					],
					[
						3.877963,
						43.614886
					],
					[
						3.877966,
						43.614886
					],
					[
						3.877969,
						43.614885
					],
					[
						3.877971,
						43.614885
					],
					[
						3.879098,
						43.614568
					],
					[
						3.879099,
						43.614569
					],
					[
						3.879099,
						43.614571
					],
					[
						3.879101,
						43.614571
					],
					[
						3.879103,
						43.614573
					],
					[
						3.879105,
						43.614575
					],
					[
						3.879106,
						43.614576
					],
					[
						3.879106,
						43.614578
					],
					[
						3.879195,
						43.61493
					],
					[
						3.879193,
						43.614931
					],
					[
						3.879191,
						43.614933
					],
					[
						3.879189,
						43.614935
					],
					[
						3.879186,
						43.614935
					],
					[
						3.879184,
						43.614936
					],
					[
						3.879183,
						43.614938
					],
					[
						3.87918,
						43.614939
					],
					[
						3.878553,
						43.615638
					],
					[
						3.878553,
						43.615638
					],
					[
						3.878553,
						43.615638
					],
					[
						3.878554,
						43.615636
					],
					[
						3.878554,
						43.615636
					],
					[
						3.878556,
						43.615635
					],
					[
						3.878556,
						43.615635
					],
					[
						3.878558,
						43.615633
					],
					[
						3.880593,
						43.614276
					],
					[
						3.880593,
						43.614276
					],
					[
						3.880593,
						43.614276
					],
					[
						3.880593,
						43.614276
					],
					[
						3.880593,
						43.614278
					],
					[
						3.880593,
						43.614278
					],
					[
						3.880593,
						43.614278
					],
					[
						3.880593,
						43.614278
					],
					[
						3.87911,
						43.615356
					],
					[
						3.879111,
						43.615355
					],
					[
						3.879113,
						43.615351
					],
					[
						3.879114,
						43.615348
					],
					[
						3.879116,
						43.615344
					],
					[
						3.879118,
						43.615341
					],
					[
						3.879121,
						43.615336
					],
					[
						3.879123,
						43.615333
					],
					[
						3.879268,
						43.614406
					],
					[
						3.879268,
						43.614406
					],
					[
						3.879268,
						43.614406
					],
					[
						3.879268,
						43.614406
					],
					[
						3.879268,
						43.614408
					],
					[
						3.879268,
						43.614408
					],
					[
						3.879268,
						43.614408
					],
					[
						3.879268,
						43.61441
					],
					[
						3.87884,
						43.614458
					],
					[
						3.878843,
						43.614458
					],
					[
						3.878846,
						43.61446
					],
					[
						3.87885,
						43.614461
					],
					[
						3.878853,
						43.614463
					],
					[
						3.878858,
						43.614464
					],
					[
						3.878863,
						43.614468
					],
					[
						3.878869,
						43.614469
					],
					[
						3.879399,
						43.614745
					],
					[
						3.879399,
						43.614745
					],
					[
						3.879399,
						43.614745
					],
					[
						3.879399,
						43.614743
					],
					[
						3.879399,
						43.614743
					],
					[
						3.879399,
						43.614743
					],
					[
						3.879399,
						43.614741
					],
					[
						3.879399,
						43.614741
					],
					[
						3.879441,
						43.614698
					],
					[
						3.879441,
						43.614698
					],
					[
						3.879441,
						43.614698
					],
					[
						3.879441,
						43.614698
					],
					[
						3.879441,
						43.614698
					],
					[
						3.879441,
						43.614698
					],
					[
						3.879441,
						43.614698
					],
					[
						3.879441,
						43.614698
					],
					[
						3.878934,
						43.614195
					],
					[
						3.878934,
						43.614195
					],
					[
						3.878936,
						43.614196
					],
					[
						3.878936,
						43.614198
					],
					[
						3.878938,
						43.614199
					],
					[
						3.878938,
						43.614201
					],
					[
						3.87894,
						43.614203
					],
					[
						3.878941,
						43.614205
					],
					[
						3.879231,
						43.614598
					],
					[
						3.879231,
						43.614598
					],
					[
						3.879231,
						43.614598
					],
					[
						3.879231,
						43.614598
					],
					[
						3.879231,
						43.614598
					],
					[
						3.879231,
						43.614598
					],
					[
						3.879231,
						43.614598
					],
					[
						3.879229,
						43.614598
					],
					[
						3.879123,
						43.614448
					],
					[
						3.879121,
						43.614446
					],
					[
						3.879121,
						43.614446
					],
					[
						3.87912,
						43.614446
					],
					[
						3.879116,
						43.614441
					],
					[
						3.879116,
						43.614438
					],
					[
						3.879114,
						43.614436
					],
					[
						3.879114,
						43.614433
					],
					[
						3.879341,
						43.613456
					],
					[
						3.879341,
						43.613456
					],
					[
						3.879341,
						43.613456
					],
					[
						3.879341,
						43.613456
					],
					[
						3.879341,
						43.613456
					],
					[
						3.879341,
						43.613456
					],
					[
						3.879341,
						43.613458
					],
					[
						3.879341,
						43.613458
					],
					[
						3.87911,
						43.613765
					],
					[
						3.87911,
						43.613765
					],
					[
						3.87911,
						43.613765
					],
					[
						3.87911,
						43.613765
					],
					[
						3.87911,
						43.613765
					],
					[
						3.87911,
						43.613765
					],
					[
						3.87911,
						43.613765
					],
					[
						3.87911,
						43.613765
					],
					[
						3.878868,
						43.61367
					],
					[
						3.878868,
						43.61367
					],
					[
						3.878869,
						43.613671
					],
					[
						3.878869,
						43.613673
					],
					[
						3.878869,
						43.613675
					],
					[
						3.878871,
						43.613675
					],
					[
						3.878871,
						43.613676
					],
					[
						3.878873,
						43.613678
					],
					[
						3.878663,
						43.613803
					],
					[
						3.878663,
						43.613803
					],
					[
						3.878663,
						43.613805
					],
					[
						3.878664,
						43.613805
					],
					[
						3.878666,
						43.613806
					],
					[
						3.878668,
						43.613806
					],
					[
						3.87867,
						43.613808
					],
					[
						3.878671,
						43.613808
					],
					[
						3.878556,
						43.615265
					],
					[
						3.878575,
						43.615231
					],
					[
						3.878616,
						43.615151
					],
					[
						3.878618,
						43.61515
					],
					[
						3.87862,
						43.615146
					],
					[
						3.878621,
						43.615143
					],
					[
						3.878623,
						43.615139
					],
					[
						3.878625,
						43.615136
					],
					[
						3.87924,
						43.614403
					],
					[
						3.87924,
						43.614403
					],
					[
						3.87924,
						43.614403
					],
					[
						3.87924,
						43.614403
					],
					[
						3.879241,
						43.614405
					],
					[
						3.879241,
						43.614405
					],
					[
						3.879241,
						43.614405
					],
					[
						3.879243,
						43.614405
					],
					[
						3.879243,
						43.614244
					],
					[
						3.879245,
						43.614246
					],
					[
						3.879246,
						43.614248
					],
					[
						3.879249,
						43.61425
					],
					[
						3.879251,
						43.614251
					],
					[
						3.879255,
						43.614253
					],
					[
						3.879256,
						43.614255
					],
					[
						3.879258,
						43.614256
					],
					[
						3.879695,
						43.614514
					],
					[
						3.879695,
						43.614513
					],
					[
						3.879693,
						43.614513
					],
					[
						3.879693,
						43.614513
					],
					[
						3.879691,
						43.614511
					],
					[
						3.879689,
						43.614511
					],
					[
						3.879688,
						43.614511
					],
					[
						3.879686,
						43.614509
					],
					[
						3.879869,
						43.614438
					],
					[
						3.879868,
						43.614438
					],
					[
						3.879868,
						43.614439
					],
					[
						3.879866,
						43.614439
					],
					[
						3.879864,
						43.614439
					],
					[
						3.879864,
						43.614441
					],
					[
						3.879863,
						43.614441
					],
					[
						3.879861,
						43.614443
					],
					[
						3.879605,
						43.614869
					],
					[
						3.879605,
						43.614869
					],
					[
						3.879606,
						43.614869
					],
					[
						3.879608,
						43.614869
					],
					[
						3.879609,
						43.614869
					],
					[
						3.879611,
						43.614868
					],
					[
						3.879669,
						43.614756
					],
					[
						3.879668,
						43.614755
					],
					[
						3.879324,
						43.614376
					],
					[
						3.879324,
						43.614376
					],
					[
						3.879324,
						43.614376
					],
					[
						3.879324,
						43.614376
					],
					[
						3.879324,
						43.614378
					],
					[
						3.879324,
						43.614378
					],
					[
						3.879324,
						43.614378
					],
					[
						3.879324,
						43.614378
					],
					[
						3.879326,
						43.614824
					],
					[
						3.879326,
						43.614824
					],
					[
						3.87933,
						43.614828
					],
					[
						3.879371,
						43.614881
					],
					[
						3.879371,
						43.614883
					],
					[
						3.879376,
						43.614908
					],
					[
						3.879376,
						43.614921
					],
					[
						3.879383,
						43.614928
					]
				]
			}
		}
	]
}