{
	"type": "FeatureCollection",
	"features": [
		{
			"type": "Feature",
			"properties": {
				"name": "2012-09-11"
			},
			"geometry": {
				"type": "LineString",
				"coordinates": [
					[
						12.95759,
						45.730558
					],
					[
						12.966924,
						45.736539
					],
					[
						12.983934,
						45.746918
					],
					[
						12.987884,
						45.755398
					],
					[
						12.991689,
						45.761898
					],
					[
						12.996895,
						45.770146
					],
					[
						13.002963,
						45.77432
					],
					[
						13.019004,
						45.771913
					],
					[
						13.035788,
						45.778341
					],
					[
						13.051239,
						45.771836
					],
					[
						13.065953,
						45.775738
					],
					[
						13.077806,
						45.787238
					],
					[
						13.078158,
						45.788441
					],
					[
						13.078208,
						45.788388
					],
					[
						13.079308,
						45.789445
					],
					[
						13.092433,
						45.79306
					],
					[
						13.112178,
						45.785771
					],
					[
						13.116168,
						45.775405
					],
					[
						13.126758,
						45.779163
					],
					[
						13.129799,
						45.786541
					],
					[
						13.146745,
						45.780543
					],
					[
						13.164486,
						45.774904
					],
					[
						13.182804,
						45.776546
					],
					[
						13.196045,
						45.788004
					],
					[
						13.191454,
						45.804055
					],
					[
						13.198625,
						45.81526
					],
					[
						13.205908,
						45.817538
					],
					[
						13.216941,
						45.816809
					],
					[
						13.218661,
						45.810739
					],
					[
						13.218533,
						45.814513
					],
					[
						13.227373,
						45.821651
					],
					[
						13.250001,
						45.827661
					],
					[
						13.270408,
						45.824153
					],
					[
						13.281971,
						45.826166
					],
					[
						13.306813,
						45.825536
					],
					[
						13.32768,
						45.827029
					],
					[
						13.33332,
						45.821504
					],
					[
						13.335881,
						45.822074
					],
					[
						13.334401,
						45.821894
					],
					[
						13.334868,
						45.822111
					],
					[
						13.336595,
						45.822315
					],
					[
						13.34647,
						45.816686
					],
					[
						13.35616,
						45.809548
					],
					[
						13.35575,
						45.809538
					],
					[
						13.355606,
						45.809633
					],
					[
						13.358668,
						45.809175
					],
					[
						13.352381,
						45.802653
					],
					[
						13.35731,
						45.789159
					],
					[
						13.363306,
						45.778438
					],
					[
						13.369,
						45.768288
					],
					[
						13.377771,
						45.764353
					],
					[
						13.39918,
						45.768314
					],
					[
						13.416313,
						45.765788
					],
					[
						13.426713,
						45.752893
					],
					[
						13.431581,
						45.753711
					],
					[
						13.433691,
						45.752433
					],
					[
						13.442915,
						45.741329
					],
					[
						13.452501,
						45.726141
					],
					[
						13.461633,
						45.709818
					],
					[
						13.462129,
						45.707963
					],
					[
						13.463245,
						45.702478
					],
					[
						13.446561,
						45.691106
					],
					[
						13.429633,
						45.680826
					],
					[
						13.409426,
						45.683466
					],
					[
						13.392928,
						45.678358
					],
					[
						13.380008,
						45.680226
					],
					[
						13.37813,
						45.680921
					],
					[
						13.377806,
						45.681043
					],
					[
						13.381538,
						45.680043
					],
					[
						13.3895,
						45.675808
					],
					[
						13.394043,
						45.677019
					],
					[
						13.394988,
						45.67712
					],
					[
						13.409978,
						45.678373
					],
					[
						13.410484,
						45.679256
					],
					[
						13.408034,
						45.679956
					],
					[
						13.398731,
						45.680366
					],
					[
						13.388374,
						45.679073
					],
					[
						13.38523,
						45.686501
					],
					[
						13.384958,
						45.687523
					],
					[
						13.383114,
						45.701276
					],
					[
						13.384169,
						45.713318
					],
					[
						13.386071,
						45.723186
					],
					[
						13.387684,
						45.727809
					],
					[
						13.388919,
						45.731481
					],
					[
						13.384438,
						45.740415
					],
					[
						13.382616,
						45.743976
					],
					[
						13.382303,
						45.744206
					],
					[
						13.382149,
						45.744774
					],
					[
						13.377973,
						45.752828
					],
					[
						13.374426,
						45.759211
					],
					[
						13.374679,
						45.759121
					],
					[
						13.374605,
						45.759229
					],
					[
						13.371788,
						45.763176
					],
					[
						13.375801,
						45.763973
					],
					[
						13.389138,
						45.766678
					],
					[
						13.402648,
						45.768878
					],
					[
						13.408038,
						45.77159
					],
					[
						13.408056,
						45.772035
					],
					[
						13.412296,
						45.781691
					],
					[
						13.409985,
						45.790604
					],
					[
						13.416051,
						45.794698
					],
					[
						13.417901,
						45.802894
					],
					[
						13.418453,
						45.802834
					],
					[
						13.418848,
						45.801279
					],
					[
						13.418848,
						45.801291
					],
					[
						13.419116,
						45.800801
					],
					[
						13.418999,
						45.800773
					],
					[
						13.419128,
						45.800793
					],
					[
						13.419258,
						45.800683
					],
					[
						13.418723,
						45.804208
					],
					[
						13.407453,
						45.805799
					],
					[
						13.396016,
						45.806458
					],
					[
						13.395316,
						45.810505
					],
					[
						13.399496,
						45.810058
					],
					[
						13.399648,
						45.809618
					],
					[
						13.399678,
						45.809625
					],
					[
						13.398968,
						45.806319
					],
					[
						13.388503,
						45.799113
					],
					[
						13.380769,
						45.787441
					],
					[
						13.373783,
						45.778266
					],
					[
						13.366581,
						45.773844
					],
					[
						13.366998,
						45.773081
					],
					[
						13.366393,
						45.772581
					],
					[
						13.370123,
						45.769603
					],
					[
						13.36979,
						45.769685
					],
					[
						13.371578,
						45.763341
					],
					[
						13.378173,
						45.752053
					],
					[
						13.381378,
						45.746268
					],
					[
						13.381383,
						45.746295
					],
					[
						13.38138,
						45.746293
					]
				]
			}
		}
	]
}